rank_validation/__init__.py
rank_validation/cli.py
rank_validation/metrics.py
rank_validation/normalise.py
rank_validation/validation_generator.py
rank_validation-1.2.0.dist-info/licenses/LICENSE
rank_validation-1.2.0.dist-info/METADATA
rank_validation-1.2.0.dist-info/WHEEL
rank_validation-1.2.0.dist-info/entry_points.txt
rank_validation-1.2.0.dist-info/top_level.txt
rank_validation-1.2.0.dist-info/RECORD
