Metadata-Version: 2.4
Name: rank_validation
Version: 1.2.0
Summary: Lightweight, vectorised ranking-metric toolkit
Home-page: https://github.com/akashkdubey/ranking_validation
Author: Akash Dubey
Author-email: akashdubey826@gmail.com
Classifier: Development Status :: 4 - Beta
Classifier: License :: OSI Approved :: MIT License
Classifier: Intended Audience :: Developers
Classifier: Intended Audience :: Science/Research
Classifier: Topic :: Scientific/Engineering :: Information Analysis
Classifier: Topic :: Text Processing :: Linguistic
Classifier: Operating System :: OS Independent
Classifier: Typing :: Typed
Requires-Python: >=3.8
License-File: LICENSE
Requires-Dist: numpy>=1.23.2
Requires-Dist: pandas>=1.4
Requires-Dist: scipy>=1.8
Requires-Dist: rbo>=0.1.1
Dynamic: author
Dynamic: author-email
Dynamic: classifier
Dynamic: description
Dynamic: description-content-type
Dynamic: home-page
Dynamic: license-file
Dynamic: requires-dist
Dynamic: requires-python
Dynamic: summary
